; Generated by UnifyWeaver WAM-JVM Target
; WamState - Warren Abstract Machine state for JVM (Krakatau format)
; Date: {{date}}

.version 52 0
.class public WamState
.super java/lang/Object

.field public pc I
.field public cp I
.field public regs Ljava/util/HashMap;
.field public heap Ljava/util/ArrayList;
.field public trail Ljava/util/ArrayList;
.field public choicePoints Ljava/util/ArrayList;
.field public code Ljava/util/ArrayList;
.field public labels Ljava/util/HashMap;

.method public <init> : ()V
    .limit stack 3
    .limit locals 1

    aload_0
    invokespecial java/lang/Object <init> ()V
    aload_0
    iconst_1
    putfield WamState pc I
    aload_0
    iconst_m1
    putfield WamState cp I
    aload_0
    new java/util/HashMap
    dup
    invokespecial java/util/HashMap <init> ()V
    putfield WamState regs Ljava/util/HashMap;
    aload_0
    new java/util/ArrayList
    dup
    invokespecial java/util/ArrayList <init> ()V
    putfield WamState heap Ljava/util/ArrayList;
    aload_0
    new java/util/ArrayList
    dup
    invokespecial java/util/ArrayList <init> ()V
    putfield WamState trail Ljava/util/ArrayList;
    aload_0
    new java/util/ArrayList
    dup
    invokespecial java/util/ArrayList <init> ()V
    putfield WamState choicePoints Ljava/util/ArrayList;
    aload_0
    new java/util/ArrayList
    dup
    invokespecial java/util/ArrayList <init> ()V
    putfield WamState code Ljava/util/ArrayList;
    aload_0
    new java/util/HashMap
    dup
    invokespecial java/util/HashMap <init> ()V
    putfield WamState labels Ljava/util/HashMap;
    return
.end method

; --- Step method (generated) ---
{{step_code}}

; --- Helper methods (generated) ---
{{helpers_code}}
