// Generated by UnifyWeaver Jamaica Target - Transitive Closure
// Predicate: {{pred}}/2 (transitive closure of {{base}})

import java.util.ArrayList;
import java.util.HashSet;
import java.util.LinkedList;
import java.util.HashMap;
import java.util.Iterator;
import java.io.BufferedReader;
import java.io.InputStreamReader;

public class {{pred_cap}}Query {

  static HashMap edges;

  // Static initializer
  static {
    %object HashMap
    putstatic edges HashMap
  }

  %default_constructor public

  public static void addFact(String from, String to) {
    Object existing;
    getstatic edges HashMap
    aload from
    invokevirtual HashMap.get(Object)Object
    astore existing
    aload existing
    ifnonnull HAS_LIST
    %object ArrayList
    astore existing
    getstatic edges HashMap
    aload from
    aload existing
    invokevirtual HashMap.put(Object, Object)Object
    pop
  HAS_LIST:
    aload existing
    checkcast ArrayList
    aload to
    invokevirtual ArrayList.add(Object)boolean
    pop
    return
  }

  public static boolean check(String start, String target) {
    HashSet visited;
    LinkedList queue;
    String current;
    Object neighbors;
    Iterator iter;
    String next;
    %object HashSet
    astore visited
    %object LinkedList
    astore queue
    aload visited
    aload start
    invokevirtual HashSet.add(Object)boolean
    pop
    aload queue
    aload start
    invokevirtual LinkedList.add(Object)boolean
    pop
  BFS_LOOP:
    aload queue
    invokevirtual LinkedList.isEmpty()boolean
    ifne NOT_FOUND
    aload queue
    invokevirtual LinkedList.poll()Object
    checkcast String
    astore current
    getstatic edges HashMap
    aload current
    invokevirtual HashMap.get(Object)Object
    astore neighbors
    aload neighbors
    ifnull BFS_LOOP
    aload neighbors
    checkcast ArrayList
    invokevirtual ArrayList.iterator()Iterator
    astore iter
  EDGE_LOOP:
    aload iter
    invokeinterface Iterator.hasNext()boolean
    ifeq BFS_LOOP
    aload iter
    invokeinterface Iterator.next()Object
    checkcast String
    astore next
    aload next
    aload target
    invokevirtual String.equals(Object)boolean
    ifne FOUND
    aload visited
    aload next
    invokevirtual HashSet.contains(Object)boolean
    ifne EDGE_LOOP
    aload visited
    aload next
    invokevirtual HashSet.add(Object)boolean
    pop
    aload queue
    aload next
    invokevirtual LinkedList.add(Object)boolean
    pop
    goto EDGE_LOOP
  FOUND:
    iconst_1
    ireturn
  NOT_FOUND:
    iconst_0
    ireturn
  }

  public static void main(String[] args) {
    java.io.InputStream sysIn;
    InputStreamReader isr;
    BufferedReader reader;
    String line;
    String[] parts;
    // Build BufferedReader(InputStreamReader(System.in))
    getstatic System.in java.io.InputStream
    astore sysIn
    %object InputStreamReader(java.io.InputStream)(sysIn)
    astore isr
    %object BufferedReader(java.io.Reader)(isr)
    astore reader
  READ_LOOP:
    aload reader
    invokevirtual BufferedReader.readLine()String
    astore line
    aload line
    ifnull READ_DONE
    aload line
    ldc ":"
    invokevirtual String.contains(CharSequence)boolean
    ifeq READ_LOOP
    aload line
    ldc ":"
    iconst_2
    invokevirtual String.split(String, int)String[]
    astore parts
    aload parts
    iconst_0
    aaload
    invokevirtual String.trim()String
    aload parts
    iconst_1
    aaload
    invokevirtual String.trim()String
    invokestatic addFact(String, String)void
    goto READ_LOOP
  READ_DONE:
    // CLI: check(args[0], args[1])
    aload args
    arraylength
    iconst_2
    if_icmpne USAGE
    aload args
    iconst_0
    aaload
    aload args
    iconst_1
    aaload
    invokestatic check(String, String)boolean
    ifeq NOT_REACHABLE
    %println args[0], ":", args[1]
    return
  NOT_REACHABLE:
    iconst_1
    invokestatic System.exit(int)void
  USAGE:
    %println <err> "Usage: {{pred}} <start> <target>"
    iconst_1
    invokestatic System.exit(int)void
  }
}
