// Generated by UnifyWeaver Jamaica Target - Transitive Closure
// Predicate: {{pred}}/2 (transitive closure of {{base}})

import java.util.ArrayList;
import java.util.HashSet;
import java.util.LinkedList;
import java.util.HashMap;

public class {{pred_cap}}Query {

  %default_constructor public

  // Edge storage
  static HashMap edges = new HashMap();

  public static void add_fact(String from, String to) {
    Object existing;
    aload from
    invokestatic {{pred_cap}}Query.edges HashMap
    invokevirtual HashMap.get(Object)Object
    astore existing
    // Create list if null
    aload existing
    ifnonnull HAS_LIST
    %object ArrayList
    astore existing
    aload from
    aload existing
    invokestatic {{pred_cap}}Query.edges HashMap
    invokevirtual HashMap.put(Object Object)Object
    pop
  HAS_LIST:
    aload existing
    checkcast ArrayList
    aload to
    invokevirtual ArrayList.add(Object)boolean
    pop
    return
  }

  public static boolean check(String start, String target) {
    // BFS reachability
    %object HashSet
    astore visited
    %object LinkedList
    astore queue
    aload visited
    aload start
    invokevirtual HashSet.add(Object)boolean
    pop
    aload queue
    aload start
    invokevirtual LinkedList.add(Object)boolean
    pop
  BFS_LOOP:
    aload queue
    invokevirtual LinkedList.isEmpty()boolean
    ifne NOT_FOUND
    aload queue
    invokevirtual LinkedList.poll()Object
    checkcast String
    astore current
    // Check edges from current
    aload current
    invokestatic {{pred_cap}}Query.edges HashMap
    invokevirtual HashMap.get(Object)Object
    astore neighbors
    aload neighbors
    ifnull BFS_LOOP
    aload neighbors
    checkcast ArrayList
    invokevirtual ArrayList.iterator()Iterator
    astore iter
  EDGE_LOOP:
    aload iter
    invokeinterface Iterator.hasNext()boolean
    ifeq BFS_LOOP
    aload iter
    invokeinterface Iterator.next()Object
    checkcast String
    astore next
    aload next
    aload target
    invokevirtual String.equals(Object)boolean
    ifne FOUND
    aload visited
    aload next
    invokevirtual HashSet.contains(Object)boolean
    ifne EDGE_LOOP
    aload visited
    aload next
    invokevirtual HashSet.add(Object)boolean
    pop
    aload queue
    aload next
    invokevirtual LinkedList.add(Object)boolean
    pop
    goto EDGE_LOOP
  FOUND:
    iconst_1
    ireturn
  NOT_FOUND:
    iconst_0
    ireturn
  }
}
