; Generated by UnifyWeaver Krakatau Target - Transitive Closure
; Predicate: {{pred}}/2 (transitive closure of {{base}})

.version 50 0
.class public {{pred_cap}}Query
.super java/lang/Object

.field static edges Ljava/util/HashMap;

.method static <clinit> : ()V
    .limit stack 2
    .limit locals 0
    new java/util/HashMap
    dup
    invokespecial java/util/HashMap <init> ()V
    putstatic {{pred_cap}}Query edges Ljava/util/HashMap;
    return
.end method

.method public static addFact : (Ljava/lang/String;Ljava/lang/String;)V
    .limit stack 3
    .limit locals 3
    getstatic {{pred_cap}}Query edges Ljava/util/HashMap;
    aload_0
    invokevirtual java/util/HashMap get (Ljava/lang/Object;)Ljava/lang/Object;
    astore_2
    aload_2
    ifnonnull LHAS_LIST
    new java/util/ArrayList
    dup
    invokespecial java/util/ArrayList <init> ()V
    astore_2
    getstatic {{pred_cap}}Query edges Ljava/util/HashMap;
    aload_0
    aload_2
    invokevirtual java/util/HashMap put (Ljava/lang/Object;Ljava/lang/Object;)Ljava/lang/Object;
    pop
LHAS_LIST:
    aload_2
    checkcast java/util/ArrayList
    aload_1
    invokevirtual java/util/ArrayList add (Ljava/lang/Object;)Z
    pop
    return
.end method

.method public static check : (Ljava/lang/String;Ljava/lang/String;)Z
    .limit stack 3
    .limit locals 6
    new java/util/HashSet
    dup
    invokespecial java/util/HashSet <init> ()V
    astore_2
    new java/util/LinkedList
    dup
    invokespecial java/util/LinkedList <init> ()V
    astore_3
    aload_2
    aload_0
    invokevirtual java/util/HashSet add (Ljava/lang/Object;)Z
    pop
    aload_3
    aload_0
    invokevirtual java/util/LinkedList add (Ljava/lang/Object;)Z
    pop
LBFS_LOOP:
    aload_3
    invokevirtual java/util/LinkedList isEmpty ()Z
    ifne LNOT_FOUND
    aload_3
    invokevirtual java/util/LinkedList poll ()Ljava/lang/Object;
    checkcast java/lang/String
    astore 4
    getstatic {{pred_cap}}Query edges Ljava/util/HashMap;
    aload 4
    invokevirtual java/util/HashMap get (Ljava/lang/Object;)Ljava/lang/Object;
    dup
    ifnull LPOP_CONTINUE
    checkcast java/util/ArrayList
    invokevirtual java/util/ArrayList iterator ()Ljava/util/Iterator;
    astore 5
LEDGE_LOOP:
    aload 5
    invokeinterface java/util/Iterator hasNext ()Z 1
    ifeq LBFS_LOOP
    aload 5
    invokeinterface java/util/Iterator next ()Ljava/lang/Object; 1
    checkcast java/lang/String
    dup
    aload_1
    invokevirtual java/lang/String equals (Ljava/lang/Object;)Z
    ifne LFOUND_POP
    dup
    aload_2
    swap
    invokevirtual java/util/HashSet contains (Ljava/lang/Object;)Z
    ifne LPOP_EDGE_CONTINUE
    dup
    aload_2
    swap
    invokevirtual java/util/HashSet add (Ljava/lang/Object;)Z
    pop
    aload_3
    swap
    invokevirtual java/util/LinkedList add (Ljava/lang/Object;)Z
    pop
    goto LEDGE_LOOP
LPOP_EDGE_CONTINUE:
    pop
    goto LEDGE_LOOP
LPOP_CONTINUE:
    pop
    goto LBFS_LOOP
LFOUND_POP:
    pop
    iconst_1
    ireturn
LNOT_FOUND:
    iconst_0
    ireturn
.end method
