
    ; CLI interface: check(args[0], args[1])
    aload_0
    arraylength
    iconst_2
    if_icmpne LUSAGE
    aload_0
    iconst_0
    aaload
    aload_0
    iconst_1
    aaload
    invokestatic {{pred_cap}}Query check (Ljava/lang/String;Ljava/lang/String;)Z
    ifeq LNOT_REACHABLE
    ; Print "start:target"
    getstatic java/lang/System out Ljava/io/PrintStream;
    new java/lang/StringBuilder
    dup
    aload_0
    iconst_0
    aaload
    invokespecial java/lang/StringBuilder <init> (Ljava/lang/String;)V
    ldc ":"
    invokevirtual java/lang/StringBuilder append (Ljava/lang/String;)Ljava/lang/StringBuilder;
    aload_0
    iconst_1
    aaload
    invokevirtual java/lang/StringBuilder append (Ljava/lang/String;)Ljava/lang/StringBuilder;
    invokevirtual java/lang/StringBuilder toString ()Ljava/lang/String;
    invokevirtual java/io/PrintStream println (Ljava/lang/String;)V
    return
LNOT_REACHABLE:
    iconst_1
    invokestatic java/lang/System exit (I)V
    return
LUSAGE:
    getstatic java/lang/System err Ljava/io/PrintStream;
    ldc "Usage: {{pred}} <start> <target>"
    invokevirtual java/io/PrintStream println (Ljava/lang/String;)V
    iconst_1
    invokestatic java/lang/System exit (I)V
    return
.end method
