; Generated by UnifyWeaver Krakatau Target - Transitive Closure
; Predicate: {{pred}}/2 (transitive closure of {{base}})

.version 52 0
.class public {{pred_cap}}Query
.super java/lang/Object

; Edge storage: HashMap<String, ArrayList<String>>
.field static edges Ljava/util/HashMap;

; Static initializer
.method static <clinit> : ()V
    .limit stack 2
    .limit locals 0

    new java/util/HashMap
    dup
    invokespecial java/util/HashMap <init> ()V
    putstatic {{pred_cap}}Query edges Ljava/util/HashMap;
    return
.end method

; add_fact(from, to): register a base relation edge
.method public static add_fact : (Ljava/lang/String;Ljava/lang/String;)V
    .limit stack 3
    .limit locals 3

    ; Get existing list for 'from'
    getstatic {{pred_cap}}Query edges Ljava/util/HashMap;
    aload_0
    invokevirtual java/util/HashMap get (Ljava/lang/Object;)Ljava/lang/Object;
    astore_2

    ; Create ArrayList if null
    aload_2
    ifnonnull HAS_LIST
    new java/util/ArrayList
    dup
    invokespecial java/util/ArrayList <init> ()V
    astore_2
    getstatic {{pred_cap}}Query edges Ljava/util/HashMap;
    aload_0
    aload_2
    invokevirtual java/util/HashMap put (Ljava/lang/Object;Ljava/lang/Object;)Ljava/lang/Object;
    pop
HAS_LIST:
    aload_2
    checkcast java/util/ArrayList
    aload_1
    invokevirtual java/util/ArrayList add (Ljava/lang/Object;)Z
    pop
    return
.end method

; check(start, target): BFS reachability
.method public static check : (Ljava/lang/String;Ljava/lang/String;)Z
    .limit stack 3
    .limit locals 6

    ; visited = new HashSet(), queue = new LinkedList()
    new java/util/HashSet
    dup
    invokespecial java/util/HashSet <init> ()V
    astore_2

    new java/util/LinkedList
    dup
    invokespecial java/util/LinkedList <init> ()V
    astore_3

    ; visited.add(start), queue.add(start)
    aload_2
    aload_0
    invokevirtual java/util/HashSet add (Ljava/lang/Object;)Z
    pop
    aload_3
    aload_0
    invokevirtual java/util/LinkedList add (Ljava/lang/Object;)Z
    pop

BFS_LOOP:
    aload_3
    invokevirtual java/util/LinkedList isEmpty ()Z
    ifne NOT_FOUND

    ; current = queue.poll()
    aload_3
    invokevirtual java/util/LinkedList poll ()Ljava/lang/Object;
    checkcast java/lang/String
    astore 4

    ; neighbors = edges.get(current)
    getstatic {{pred_cap}}Query edges Ljava/util/HashMap;
    aload 4
    invokevirtual java/util/HashMap get (Ljava/lang/Object;)Ljava/lang/Object;
    dup
    ifnull POP_CONTINUE
    checkcast java/util/ArrayList
    invokevirtual java/util/ArrayList iterator ()Ljava/util/Iterator;
    astore 5

EDGE_LOOP:
    aload 5
    invokeinterface java/util/Iterator hasNext ()Z 1
    ifeq BFS_LOOP

    aload 5
    invokeinterface java/util/Iterator next ()Ljava/lang/Object; 1
    checkcast java/lang/String
    dup

    ; if next.equals(target) -> found
    aload_1
    invokevirtual java/lang/String equals (Ljava/lang/Object;)Z
    ifne FOUND_POP

    ; if not visited, add to queue
    dup
    aload_2
    swap
    invokevirtual java/util/HashSet contains (Ljava/lang/Object;)Z
    ifne POP_EDGE_CONTINUE

    dup
    aload_2
    swap
    invokevirtual java/util/HashSet add (Ljava/lang/Object;)Z
    pop
    aload_3
    swap
    invokevirtual java/util/LinkedList add (Ljava/lang/Object;)Z
    pop
    goto EDGE_LOOP

POP_EDGE_CONTINUE:
    pop
    goto EDGE_LOOP

POP_CONTINUE:
    pop
    goto BFS_LOOP

FOUND_POP:
    pop
    iconst_1
    ireturn

NOT_FOUND:
    iconst_0
    ireturn
.end method
